ezactions/__init__.py
ezactions-0.0.2.dist-info/METADATA
ezactions-0.0.2.dist-info/WHEEL
ezactions-0.0.2.dist-info/top_level.txt
ezactions-0.0.2.dist-info/RECORD
