Metadata-Version: 2.1
Name: ezactions
Version: 0.0.2
Summary: Demo project
Author-email: Thuyen Trinh <trinhngocthuyen@gmail.com>
License: MIT
Project-URL: Homepage, https://github.com/trinhngocthuyen/ezactions
Classifier: License :: OSI Approved :: MIT License
Classifier: Programming Language :: Python
Classifier: Programming Language :: Python :: 3
Classifier: Programming Language :: Python :: 3.8
Classifier: Programming Language :: Python :: 3.9
Classifier: Programming Language :: Python :: 3.10
Requires-Python: >=3.8
Requires-Dist: requests
Provides-Extra: dev
Requires-Dist: black; extra == "dev"
Requires-Dist: autoflake; extra == "dev"
Requires-Dist: bumpver; extra == "dev"
Requires-Dist: isort; extra == "dev"
Requires-Dist: pip-tools; extra == "dev"
Requires-Dist: pytest; extra == "dev"
Requires-Dist: twine; extra == "dev"
Requires-Dist: setuptools>=61.0.0; extra == "dev"
